mdft/__init__.py
mdft/__main__.py
mdft/converter/__init__.py
mdft/converter/converter.py
mdft/file/__init__.py
mdft/file/file.py
mdft/injector/__init__.py
mdft/injector/injector.py
mdft/scanner/__init__.py
mdft/scanner/file_filter.py
mdft/scanner/file_scanner.py
mdft/util/__init__.py
mdft/util/blueprint.py
mdft/util/command.py
mdft/util/line.py
mdft/util/options.py
mdft-0.1.6.dist-info/LICENSE
mdft-0.1.6.dist-info/METADATA
mdft-0.1.6.dist-info/WHEEL
mdft-0.1.6.dist-info/top_level.txt
mdft-0.1.6.dist-info/RECORD
