Metadata-Version: 2.1
Name: mdft
Version: 0.1.6
Summary: Package for generating file trees in Markdown
Author-email: Rafael Copstein <rcopstein@gmail.com>
Project-URL: Homepage, https://github.com/rcopstein/mdft
Project-URL: Issues, https://github.com/rcopstein/mdft/issues
Classifier: Operating System :: OS Independent
Classifier: Programming Language :: Python :: 3
Classifier: License :: OSI Approved :: GNU General Public License v3 (GPLv3)
Requires-Python: >=3.9
License-File: LICENSE
Requires-Dist: pathspec>=0.12.1
